onetomultipleimage/__init__.py
onetomultipleimage/apps.py
onetomultipleimage/fields.py
onetomultipleimage/methods.py
onetomultipleimage/models.py
onetomultipleimage/migrations/0001_initial.py
onetomultipleimage/migrations/0002_image_sizes.py
onetomultipleimage/migrations/0003_rename_image_fatherimage.py
onetomultipleimage/migrations/0004_remove_imagesizes_father_delete_fatherimage_and_more.py
onetomultipleimage/migrations/0005_initial.py
onetomultipleimage/migrations/0006_alter_fatherimage_table_alter_imagesizes_table.py
onetomultipleimage/migrations/__init__.py
onetomultipleimage_test-1.0.0.dist-info/LICENSE
onetomultipleimage_test-1.0.0.dist-info/METADATA
onetomultipleimage_test-1.0.0.dist-info/WHEEL
onetomultipleimage_test-1.0.0.dist-info/top_level.txt
onetomultipleimage_test-1.0.0.dist-info/RECORD
